sidita/Message.py
sidita/Statistics.py
sidita/TaskMetaData.py
sidita/TaskQueue.py
sidita/Units.py
sidita/Worker.py
sidita/WorkerMetrics.py
sidita/__init__.py
sidita/worker.py
sidita/Logging/__init__.py
sidita/Logging/logging.yml
sidita-1.0.1.dist-info/METADATA
sidita-1.0.1.dist-info/RECORD
sidita-1.0.1.dist-info/WHEEL
sidita-1.0.1.dist-info/top_level.txt
