Metadata-Version: 2.1
Name: sidita
Version: 1.0.1
Summary: Simple Distributed Task Queue : multiprocessing < sidita < celery
Home-page: https://github.com/FabriceSalvaire/sidita
Author: Fabrice Salvaire
Author-email: fabrice.salvaire@orange.fr
License: GPLv3
Keywords: distributed task queue asyncio multiprocessing
Platform: any
Classifier: Development Status :: 5 - Production/Stable
Classifier: Framework :: AsyncIO
Classifier: Intended Audience :: Developers
Classifier: License :: OSI Approved :: GNU General Public License v3 (GPLv3)
Classifier: Operating System :: OS Independent
Classifier: Programming Language :: Python :: 3.6
Classifier: Programming Language :: Python :: Implementation :: CPython
Classifier: Topic :: System :: Distributed Computing
Classifier: Topic :: System :: Hardware :: Symmetric Multi-processing
Requires-Dist: PyYAML (>=3.10)
Requires-Dist: psutil (>=5.4.3)
